antics/__init__.py
antics/greetings.py
voidnet-0.0.1.dist-info/licenses/LICENSE
voidnet-0.0.1.dist-info/METADATA
voidnet-0.0.1.dist-info/WHEEL
voidnet-0.0.1.dist-info/entry_points.txt
voidnet-0.0.1.dist-info/top_level.txt
voidnet-0.0.1.dist-info/RECORD
